{"name":"Inicio sesion invalido","id":"yo-como-administrativo-puedo-iniciar-sesion-en-el-aplicativo;inicio-sesion-invalido","testSteps":[{"number":1,"description":"Example: {users\u003dAdmin, pass\u003dadmin124, mensaje\u003dInvalid credentials}","duration":7671,"startTime":"2021-10-24T22:40:05.723-05:00[America/Bogota]","screenshots":[{"screenshot":"388b4a4c2d3e65e7713db814219d3ce49d05cf2091e96bf8d96054e007582dd3.png","timeStamp":1635133213394}],"result":"SUCCESS","precondition":false,"level":0,"lineNumber":12,"children":[{"number":2,"description":"Given necesito ingresar al sistema OrangHRM","duration":4031,"startTime":"2021-10-24T22:40:05.723-05:00[America/Bogota]","screenshots":[{"screenshot":"7827ac1b776525448fe6d3aadb140c9ca2f844e99f09df8e5fa9f5f47e5ac6aa.png","timeStamp":1635133209754}],"result":"SUCCESS","precondition":false,"level":1,"children":[{"number":3,"description":"Usuario open landing page","duration":2092,"startTime":"2021-10-24T22:40:07.662-05:00[America/Bogota]","screenshots":[{"screenshot":"ee6d3ff44e8ef974602278668268ddc3a8113b25f52c2f8566de86faa63027cc.png","timeStamp":1635133207859},{"screenshot":"7827ac1b776525448fe6d3aadb140c9ca2f844e99f09df8e5fa9f5f47e5ac6aa.png","timeStamp":1635133209754}],"result":"SUCCESS","precondition":false,"level":2,"children":[{"number":4,"description":"Usuario opens the Landing page","duration":1880,"startTime":"2021-10-24T22:40:07.859-05:00[America/Bogota]","screenshots":[{"screenshot":"ee6d3ff44e8ef974602278668268ddc3a8113b25f52c2f8566de86faa63027cc.png","timeStamp":1635133207875},{"screenshot":"7827ac1b776525448fe6d3aadb140c9ca2f844e99f09df8e5fa9f5f47e5ac6aa.png","timeStamp":1635133209739}],"result":"SUCCESS","precondition":false,"level":3}]}]},{"number":5,"description":"When ingreso un usuario Admin, una contraseña admin124","duration":3183,"startTime":"2021-10-24T22:40:09.754-05:00[America/Bogota]","screenshots":[{"screenshot":"7827ac1b776525448fe6d3aadb140c9ca2f844e99f09df8e5fa9f5f47e5ac6aa.png","timeStamp":1635133209754},{"screenshot":"388b4a4c2d3e65e7713db814219d3ce49d05cf2091e96bf8d96054e007582dd3.png","timeStamp":1635133212937}],"result":"SUCCESS","precondition":false,"level":1,"children":[{"number":6,"description":"Usuario fill p login form","duration":3183,"startTime":"2021-10-24T22:40:09.754-05:00[America/Bogota]","screenshots":[{"screenshot":"7827ac1b776525448fe6d3aadb140c9ca2f844e99f09df8e5fa9f5f47e5ac6aa.png","timeStamp":1635133209754},{"screenshot":"388b4a4c2d3e65e7713db814219d3ce49d05cf2091e96bf8d96054e007582dd3.png","timeStamp":1635133212937}],"result":"SUCCESS","precondition":false,"level":2,"children":[{"number":7,"description":"Usuario enters \u0027Admin\u0027 into Nombre usuario","duration":682,"startTime":"2021-10-24T22:40:09.806-05:00[America/Bogota]","screenshots":[{"screenshot":"d68b07cdfc8cdd4204b38cf43d9fc27ba492fc071222538c8bf8c6cb58bf5822.png","timeStamp":1635133210056},{"screenshot":"a4d0e655d62efccba1bba14974db89aa4deec767bd63ec1f9ecf506a2c3f28da.png","timeStamp":1635133210488}],"result":"SUCCESS","precondition":false,"level":3},{"number":8,"description":"Usuario enters \u0027admin124\u0027 into Contraseña","duration":732,"startTime":"2021-10-24T22:40:10.551-05:00[America/Bogota]","screenshots":[{"screenshot":"a4d0e655d62efccba1bba14974db89aa4deec767bd63ec1f9ecf506a2c3f28da.png","timeStamp":1635133210815},{"screenshot":"5222778c3bf2dcfed3c06b2e8aec7aaf59e84749da3f4c7e2fb7d9287b4ea665.png","timeStamp":1635133211283}],"result":"SUCCESS","precondition":false,"level":3},{"number":9,"description":"Usuario clicks on Botón Login","duration":1577,"startTime":"2021-10-24T22:40:11.345-05:00[America/Bogota]","screenshots":[{"screenshot":"5222778c3bf2dcfed3c06b2e8aec7aaf59e84749da3f4c7e2fb7d9287b4ea665.png","timeStamp":1635133211671},{"screenshot":"388b4a4c2d3e65e7713db814219d3ce49d05cf2091e96bf8d96054e007582dd3.png","timeStamp":1635133212922}],"result":"SUCCESS","precondition":false,"level":3}]}]},{"number":10,"description":"Then al dar click en el boton Login Invalid credentials","duration":457,"startTime":"2021-10-24T22:40:12.937-05:00[America/Bogota]","screenshots":[{"screenshot":"388b4a4c2d3e65e7713db814219d3ce49d05cf2091e96bf8d96054e007582dd3.png","timeStamp":1635133212937},{"screenshot":"388b4a4c2d3e65e7713db814219d3ce49d05cf2091e96bf8d96054e007582dd3.png","timeStamp":1635133213394}],"result":"SUCCESS","precondition":false,"level":1,"children":[{"number":11,"description":"Then login message should be (true)","duration":363,"startTime":"2021-10-24T22:40:13.031-05:00[America/Bogota]","screenshots":[{"screenshot":"388b4a4c2d3e65e7713db814219d3ce49d05cf2091e96bf8d96054e007582dd3.png","timeStamp":1635133213363},{"screenshot":"388b4a4c2d3e65e7713db814219d3ce49d05cf2091e96bf8d96054e007582dd3.png","timeStamp":1635133213394}],"result":"SUCCESS","precondition":false,"level":2}]}]},{"number":12,"description":"Example: {users\u003dadmi, pass\u003dadmin123, mensaje\u003dInvalid credentials}","duration":7577,"startTime":"2021-10-24T22:40:14.132-05:00[America/Bogota]","screenshots":[{"screenshot":"388b4a4c2d3e65e7713db814219d3ce49d05cf2091e96bf8d96054e007582dd3.png","timeStamp":1635133221709}],"result":"SUCCESS","precondition":false,"level":0,"lineNumber":13,"children":[{"number":13,"description":"Given necesito ingresar al sistema OrangHRM","duration":4256,"startTime":"2021-10-24T22:40:14.132-05:00[America/Bogota]","screenshots":[{"screenshot":"7827ac1b776525448fe6d3aadb140c9ca2f844e99f09df8e5fa9f5f47e5ac6aa.png","timeStamp":1635133218388}],"result":"SUCCESS","precondition":false,"level":1,"children":[{"number":14,"description":"Usuario open landing page","duration":2454,"startTime":"2021-10-24T22:40:15.919-05:00[America/Bogota]","screenshots":[{"screenshot":"ee6d3ff44e8ef974602278668268ddc3a8113b25f52c2f8566de86faa63027cc.png","timeStamp":1635133216135},{"screenshot":"7827ac1b776525448fe6d3aadb140c9ca2f844e99f09df8e5fa9f5f47e5ac6aa.png","timeStamp":1635133218373}],"result":"SUCCESS","precondition":false,"level":2,"children":[{"number":15,"description":"Usuario opens the Landing page","duration":2238,"startTime":"2021-10-24T22:40:16.135-05:00[America/Bogota]","screenshots":[{"screenshot":"ee6d3ff44e8ef974602278668268ddc3a8113b25f52c2f8566de86faa63027cc.png","timeStamp":1635133216150},{"screenshot":"7827ac1b776525448fe6d3aadb140c9ca2f844e99f09df8e5fa9f5f47e5ac6aa.png","timeStamp":1635133218373}],"result":"SUCCESS","precondition":false,"level":3}]}]},{"number":16,"description":"When ingreso un usuario admi, una contraseña admin123","duration":3274,"startTime":"2021-10-24T22:40:18.388-05:00[America/Bogota]","screenshots":[{"screenshot":"7827ac1b776525448fe6d3aadb140c9ca2f844e99f09df8e5fa9f5f47e5ac6aa.png","timeStamp":1635133218388},{"screenshot":"388b4a4c2d3e65e7713db814219d3ce49d05cf2091e96bf8d96054e007582dd3.png","timeStamp":1635133221662}],"result":"SUCCESS","precondition":false,"level":1,"children":[{"number":17,"description":"Usuario fill p login form","duration":3274,"startTime":"2021-10-24T22:40:18.388-05:00[America/Bogota]","screenshots":[{"screenshot":"7827ac1b776525448fe6d3aadb140c9ca2f844e99f09df8e5fa9f5f47e5ac6aa.png","timeStamp":1635133218388},{"screenshot":"388b4a4c2d3e65e7713db814219d3ce49d05cf2091e96bf8d96054e007582dd3.png","timeStamp":1635133221662}],"result":"SUCCESS","precondition":false,"level":2,"children":[{"number":18,"description":"Usuario enters \u0027admi\u0027 into Nombre usuario","duration":965,"startTime":"2021-10-24T22:40:18.456-05:00[America/Bogota]","screenshots":[{"screenshot":"d68b07cdfc8cdd4204b38cf43d9fc27ba492fc071222538c8bf8c6cb58bf5822.png","timeStamp":1635133218854},{"screenshot":"060161226881417798281f2f7915059c4d25c184b54dd847aac9a62c8cc7a665.png","timeStamp":1635133219421}],"result":"SUCCESS","precondition":false,"level":3},{"number":19,"description":"Usuario enters \u0027admin123\u0027 into Contraseña","duration":1104,"startTime":"2021-10-24T22:40:19.484-05:00[America/Bogota]","screenshots":[{"screenshot":"060161226881417798281f2f7915059c4d25c184b54dd847aac9a62c8cc7a665.png","timeStamp":1635133219983},{"screenshot":"2e3613824454c3e29eef4a66617a27d74280a2dafbdb314f9c556036e6a77c12.png","timeStamp":1635133220588}],"result":"SUCCESS","precondition":false,"level":3},{"number":20,"description":"Usuario clicks on Botón Login","duration":1027,"startTime":"2021-10-24T22:40:20.635-05:00[America/Bogota]","screenshots":[{"screenshot":"2e3613824454c3e29eef4a66617a27d74280a2dafbdb314f9c556036e6a77c12.png","timeStamp":1635133220635},{"screenshot":"388b4a4c2d3e65e7713db814219d3ce49d05cf2091e96bf8d96054e007582dd3.png","timeStamp":1635133221662}],"result":"SUCCESS","precondition":false,"level":3}]}]},{"number":21,"description":"Then al dar click en el boton Login Invalid credentials","duration":47,"startTime":"2021-10-24T22:40:21.662-05:00[America/Bogota]","screenshots":[{"screenshot":"388b4a4c2d3e65e7713db814219d3ce49d05cf2091e96bf8d96054e007582dd3.png","timeStamp":1635133221709}],"result":"SUCCESS","precondition":false,"level":1,"children":[{"number":22,"description":"Then login message should be (true)","duration":32,"startTime":"2021-10-24T22:40:21.677-05:00[America/Bogota]","screenshots":[{"screenshot":"388b4a4c2d3e65e7713db814219d3ce49d05cf2091e96bf8d96054e007582dd3.png","timeStamp":1635133221709}],"result":"SUCCESS","precondition":false,"level":2}]}]}],"userStory":{"id":"yo-como-administrativo-puedo-iniciar-sesion-en-el-aplicativo","storyName":"Yo como administrativo puedo iniciar sesion en el aplicativo","path":"file:///C:/Users/YEISON/Downloads/automationtesting-trunk/webUIToolsQA/src/test/resources/features/orangehrm/login/login.feature","type":"feature"},"featureTag":{"name":"Login/Yo como administrativo puedo iniciar sesion en el aplicativo","type":"feature","displayName":"Login/Yo como administrativo puedo iniciar sesion en el aplicativo"},"title":"Inicio sesion invalido","backgroundTitle":"","backgroundDescription":"","tags":[{"name":"Orangehrm","type":"theme","displayName":"Orangehrm"},{"name":"Login/Yo como administrativo puedo iniciar sesion en el aplicativo","type":"feature","displayName":"Yo como administrativo puedo iniciar sesion en el aplicativo"},{"name":"Orangehrm/Login","type":"theme","displayName":"Login"}],"startTime":"2021-10-24T22:40:05.723-05:00[America/Bogota]","duration":16789,"projectKey":"","driver":"chrome","isManualTestingUpToDate":false,"dataTable":{"headers":["users","pass","mensaje"],"rows":[{"values":["Admin","admin124","Invalid credentials"],"lineNumber":12,"result":"SUCCESS"},{"values":["admi","admin123","Invalid credentials"],"lineNumber":13,"result":"SUCCESS"}],"predefinedRows":true,"scenarioOutline":"When ingreso un usuario \u003cusers\u003e, una contraseña \u003cpass\u003e\n\rThen al dar click en el boton Login \u003cmensaje\u003e\n\r","dataSetDescriptors":[{"startRow":0,"rowCount":0,"name":""}]},"manual":false,"testSource":"Cucumber","actors":[{"name":"Usuario","can":["browse the web"]}],"result":"SUCCESS","scenarioOutline":"When ingreso un usuario \u003cusers\u003e, una contraseña \u003cpass\u003e\r\nThen al dar click en el boton Login \u003cmensaje\u003e"}